README.txt
setup.cfg
setup.py
asc2wp/__init__.py
asc2wp/asc2wp.py
asc2wp.egg-info/PKG-INFO
asc2wp.egg-info/SOURCES.txt
asc2wp.egg-info/dependency_links.txt
asc2wp.egg-info/entry_points.txt
asc2wp.egg-info/requires.txt
asc2wp.egg-info/top_level.txt
asc2wp.egg-info/zip-safe