Metadata-Version: 1.1
Name: asc2wp
Version: 0.6.6
Summary: File base post to Wordpress with Asciidoc format
Home-page: UNKNOWN
Author: Shuichi Minamie
Author-email: s.minamie@gmail.com
License: MIT
Keywords: wordpress,asciidoc,asciidoctor,markup,api
Platform: UNKNOWN
Classifier: Environment :: Console
Classifier: Intended Audience :: Developers
Classifier: Natural Language :: English
Classifier: Programming Language :: Python :: 2.7
Classifier: Programming Language :: Python :: 2 :: Only
Classifier: Topic :: Internet :: WWW/HTTP :: Dynamic Content :: News/Diary
Classifier: Topic :: Internet :: WWW/HTTP :: Site Management
Classifier: Topic :: Text Processing :: Markup
Classifier: License :: OSI Approved :: MIT License
